swft/__init__.py
swft/swft.py
swft/test.py
swft-0.3.dist-info/LICENSE
swft-0.3.dist-info/METADATA
swft-0.3.dist-info/WHEEL
swft-0.3.dist-info/top_level.txt
swft-0.3.dist-info/RECORD
