Metadata-Version: 2.1
Name: swft
Version: 0.3
Summary: Process swft files
Home-page: UNKNOWN
Author: Marc Endesfelder
Author-email: marc@endesfelder.de
License: MIT
Platform: UNKNOWN
Classifier: Development Status :: 4 - Beta
Classifier: Programming Language :: Python :: 2
Classifier: Programming Language :: Python :: 3
Classifier: License :: OSI Approved :: MIT License
Classifier: Operating System :: OS Independent
Classifier: Intended Audience :: Science/Research
Classifier: Topic :: Scientific/Engineering :: Bio-Informatics
Requires-Dist: numpy
Requires-Dist: pandas
